SecureDataTransfer/__init__.py
SecureDataTransfer/asymmetricRSAEncrypt.py
SecureDataTransfer/decrypt.py
SecureDataTransfer/mainGUI.py
SecureDataTransfer/secure_data_transfer.py
SecureDataTransfer/symmetricEncryptAES.py
secureDataTransfer-1.1.dist-info/LICENSE
secureDataTransfer-1.1.dist-info/METADATA
secureDataTransfer-1.1.dist-info/WHEEL
secureDataTransfer-1.1.dist-info/entry_points.txt
secureDataTransfer-1.1.dist-info/top_level.txt
secureDataTransfer-1.1.dist-info/RECORD
