Metadata-Version: 2.1
Name: secureDataTransfer
Version: 1.1
Summary: The 'Secure Data Transfer'  seamlessly is a robust solution for safeguarding and sharing sensitive information.
Author: Marzouq
Author-email: 01marzouq@gmail.com
License-File: LICENSE
Requires-Dist: pycryptodome >=3.10.1
Requires-Dist: pyqt5
